datafaucet/__init__.py
datafaucet/_version.py
datafaucet/crypto.py
datafaucet/data.py
datafaucet/decorators.py
datafaucet/download.py
datafaucet/engines.py
datafaucet/files.py
datafaucet/git.py
datafaucet/io.py
datafaucet/logging.py
datafaucet/metadata.py
datafaucet/paths.py
datafaucet/project.py
datafaucet/resources.py
datafaucet/utils.py
datafaucet/yaml.py
datafaucet/cli/__init__.py
datafaucet/cli/application.py
datafaucet/cli/command.py
datafaucet/cli/init.py
datafaucet/cli/run.py
datafaucet/cli/templates/metadata.ignore.yml
datafaucet/cli/templates/default/cookiecutter.json
datafaucet/cli/templates/default/{{cookiecutter.project_name}}/.editorconfig
datafaucet/cli/templates/default/{{cookiecutter.project_name}}/.gitignore
datafaucet/cli/templates/default/{{cookiecutter.project_name}}/Makefile
datafaucet/cli/templates/default/{{cookiecutter.project_name}}/README.md
datafaucet/cli/templates/default/{{cookiecutter.project_name}}/__main__.py
datafaucet/cli/templates/default/{{cookiecutter.project_name}}/main.ipynb
datafaucet/cli/templates/default/{{cookiecutter.project_name}}/metadata.yml
datafaucet/cli/templates/default/{{cookiecutter.project_name}}/binder/README.md
datafaucet/cli/templates/default/{{cookiecutter.project_name}}/binder/environment.yml
datafaucet/cli/templates/default/{{cookiecutter.project_name}}/metadata/README.md
datafaucet/cli/templates/default/{{cookiecutter.project_name}}/resources/doc/README.md
datafaucet/cli/templates/default/{{cookiecutter.project_name}}/resources/img/README.md
datafaucet/cli/templates/ingest/cookiecutter.json
datafaucet/cli/templates/ingest/{{cookiecutter.project_name}}/.editorconfig
datafaucet/cli/templates/ingest/{{cookiecutter.project_name}}/.gitignore
datafaucet/cli/templates/ingest/{{cookiecutter.project_name}}/.gitlab-ci.yml
datafaucet/cli/templates/ingest/{{cookiecutter.project_name}}/README.md
datafaucet/cli/templates/ingest/{{cookiecutter.project_name}}/__main__.py
datafaucet-0.10.0.dist-info/LICENSE
datafaucet-0.10.0.dist-info/METADATA
datafaucet-0.10.0.dist-info/WHEEL
datafaucet-0.10.0.dist-info/top_level.txt
datafaucet-0.10.0.dist-info/RECORD
